qmem/__init__.py
qmem/api.py
qmem/cache.py
qmem/cli.py
qmem/client.py
qmem/config.py
qmem/embedder.py
qmem/mongo_sink.py
qmem/py.typed
qmem/schemas.py
qmem-0.2.1.dist-info/METADATA
qmem-0.2.1.dist-info/WHEEL
qmem-0.2.1.dist-info/entry_points.txt
qmem-0.2.1.dist-info/top_level.txt
qmem-0.2.1.dist-info/RECORD
