Metadata-Version: 2.4
Name: qmem
Version: 0.2.1
Summary: Memory library for seamless data ingestion, storage, and retrieval with customizable embedding models.
Author-email: Aniruddha <aniruddhabolakhe2907@gmail.com>
License: MIT
Keywords: vector-db,rag,embeddings,retrieval
Classifier: Development Status :: 3 - Alpha
Classifier: Intended Audience :: Developers
Classifier: License :: OSI Approved :: MIT License
Classifier: Programming Language :: Python :: 3
Classifier: Programming Language :: Python :: 3 :: Only
Classifier: Programming Language :: Python :: 3.9
Classifier: Programming Language :: Python :: 3.10
Classifier: Programming Language :: Python :: 3.11
Classifier: Programming Language :: Python :: 3.12
Classifier: Topic :: Database
Classifier: Topic :: Scientific/Engineering :: Information Analysis
Requires-Python: >=3.9
Requires-Dist: qdrant-client>=1.7.0
Requires-Dist: pydantic>=2.6
Requires-Dist: typer>=0.12
Requires-Dist: rich>=13.7
Requires-Dist: tomlkit>=0.12
Requires-Dist: questionary>=2.0
Requires-Dist: openai>=1.30.0
Requires-Dist: huggingface_hub>=0.24
Requires-Dist: pymongo>=4.7
Requires-Dist: google-generativeai>=0.5.0
Requires-Dist: voyageai>=0.1.8
Requires-Dist: chromadb>=0.5
Provides-Extra: minilm
Requires-Dist: sentence-transformers>=2.6; extra == "minilm"
Requires-Dist: torch>=2; platform_machine != "wasm32" and extra == "minilm"
